gptme_rag/__init__.py
gptme_rag/__main__.py
gptme_rag/benchmark.py
gptme_rag/cli.py
gptme_rag/indexing/__init__.py
gptme_rag/indexing/document.py
gptme_rag/indexing/document_processor.py
gptme_rag/indexing/indexer.py
gptme_rag/indexing/watcher.py
gptme_rag/query/__init__.py
gptme_rag/query/context_assembler.py
gptme_rag/storage/__init__.py
gptme_rag/utils/__init__.py
gptme_rag-0.5.1.dist-info/LICENSE
gptme_rag-0.5.1.dist-info/METADATA
gptme_rag-0.5.1.dist-info/WHEEL
gptme_rag-0.5.1.dist-info/entry_points.txt
gptme_rag-0.5.1.dist-info/RECORD
