Metadata-Version: 2.1
Name: gptme-rag
Version: 0.5.1
Summary: RAG implementation for gptme context management
Home-page: https://github.com/ErikBjare/gptme-rag
License: MIT
Keywords: rag,gptme,context-management,embeddings,chromadb
Author: Bob
Author-email: bob@gptme.org
Requires-Python: >=3.10,<3.13
Classifier: Development Status :: 4 - Beta
Classifier: Environment :: Console
Classifier: Intended Audience :: Developers
Classifier: License :: OSI Approved :: MIT License
Classifier: Programming Language :: Python :: 3
Classifier: Programming Language :: Python :: 3.10
Classifier: Programming Language :: Python :: 3.11
Classifier: Programming Language :: Python :: 3.12
Classifier: Topic :: Software Development :: Libraries :: Python Modules
Classifier: Topic :: Text Processing :: General
Requires-Dist: chromadb (>=0.4,<0.5)
Requires-Dist: click
Requires-Dist: numpy (<2.0.0)
Requires-Dist: psutil (>=6.1.0,<7.0.0)
Requires-Dist: rich
Requires-Dist: tiktoken (>=0.7)
Requires-Dist: tqdm (>=4.67.1,<5.0.0)
Requires-Dist: watchdog (>=3.0.0,<4.0.0)
Project-URL: Documentation, https://github.com/ErikBjare/gptme-rag#readme
Project-URL: Repository, https://github.com/ErikBjare/gptme-rag
